<?xml version="1.0" encoding="UTF-8"?>
<trophy type="filesmanager" version="1.1.0.0" description="Files manager" archived="0">
	<trophyheader version="1.0.0.0">
		<accesslog>
			<creation datetime="2021-08-04T19:25:17+0000" applicationname="CS 3D Imaging" applicationversion="3.8.7.0" />
			<modification datetime="2021-08-04T20:10:35+0000" applicationname="CS 3D Imaging" applicationversion="3.8.7.0" />
			<modification datetime="2022-04-08T14:11:13+0000" applicationname="CS 3D Imaging" applicationversion="3.8.6.0" />
		</accesslog>
	</trophyheader>
	<FilesManager Version="1.0" Uid="1.2.250.1.90.1.913119188.20210804152517.10864.2">
		<Files>
			<File Uid="0" Path="3DSlice1.dcm" Type="Volume" />
			<File Uid="0" Path="3DSlice10.dcm" Type="Volume" />
			<File Uid="0" Path="3DSlice100.dcm" Type="Volume" />
			<File Uid="0" Path="3DSlice101.dcm" Type="Volume" />
			<File Uid="0" Path="3DSlice102.dcm" Type="Volume" />
			<File Uid="0" Path="3DSlice103.dcm" Type="Volume" />
			<File Uid="0" Path="3DSlice104.dcm" Type="Volume" />
			<File Uid="0" Path="3DSlice105.dcm" Type="Volume" />
			<File Uid="0" Path="3DSlice106.dcm" Type="Volume" />
			<File Uid="0" Path="3DSlice107.dcm" Type="Volume" />
			<File Uid="0" Path="3DSlice108.dcm" Type="Volume" />
			<File Uid="0" Path="3DSlice109.dcm" Type="Volume" />
			<File Uid="0" Path="3DSlice11.dcm" Type="Volume" />
			<File Uid="0" Path="3DSlice110.dcm" Type="Volume" />
			<File Uid="0" Path="3DSlice111.dcm" Type="Volume" />
			<File Uid="0" Path="3DSlice112.dcm" Type="Volume" />
			<File Uid="0" Path="3DSlice113.dcm" Type="Volume" />
			<File Uid="0" Path="3DSlice114.dcm" Type="Volume" />
			<File Uid="0" Path="3DSlice115.dcm" Type="Volume" />
			<File Uid="0" Path="3DSlice116.dcm" Type="Volume" />
			<File Uid="0" Path="3DSlice117.dcm" Type="Volume" />
			<File Uid="0" Path="3DSlice118.dcm" Type="Volume" />
			<File Uid="0" Path="3DSlice119.dcm" Type="Volume" />
			<File Uid="0" Path="3DSlice12.dcm" Type="Volume" />
			<File Uid="0" Path="3DSlice120.dcm" Type="Volume" />
			<File Uid="0" Path="3DSlice121.dcm" Type="Volume" />
			<File Uid="0" Path="3DSlice122.dcm" Type="Volume" />
			<File Uid="0" Path="3DSlice123.dcm" Type="Volume" />
			<File Uid="0" Path="3DSlice124.dcm" Type="Volume" />
			<File Uid="0" Path="3DSlice125.dcm" Type="Volume" />
			<File Uid="0" Path="3DSlice126.dcm" Type="Volume" />
			<File Uid="0" Path="3DSlice127.dcm" Type="Volume" />
			<File Uid="0" Path="3DSlice128.dcm" Type="Volume" />
			<File Uid="0" Path="3DSlice129.dcm" Type="Volume" />
			<File Uid="0" Path="3DSlice13.dcm" Type="Volume" />
			<File Uid="0" Path="3DSlice130.dcm" Type="Volume" />
			<File Uid="0" Path="3DSlice131.dcm" Type="Volume" />
			<File Uid="0" Path="3DSlice132.dcm" Type="Volume" />
			<File Uid="0" Path="3DSlice133.dcm" Type="Volume" />
			<File Uid="0" Path="3DSlice134.dcm" Type="Volume" />
			<File Uid="0" Path="3DSlice135.dcm" Type="Volume" />
			<File Uid="0" Path="3DSlice136.dcm" Type="Volume" />
			<File Uid="0" Path="3DSlice137.dcm" Type="Volume" />
			<File Uid="0" Path="3DSlice138.dcm" Type="Volume" />
			<File Uid="0" Path="3DSlice139.dcm" Type="Volume" />
			<File Uid="0" Path="3DSlice14.dcm" Type="Volume" />
			<File Uid="0" Path="3DSlice140.dcm" Type="Volume" />
			<File Uid="0" Path="3DSlice141.dcm" Type="Volume" />
			<File Uid="0" Path="3DSlice142.dcm" Type="Volume" />
			<File Uid="0" Path="3DSlice143.dcm" Type="Volume" />
			<File Uid="0" Path="3DSlice144.dcm" Type="Volume" />
			<File Uid="0" Path="3DSlice145.dcm" Type="Volume" />
			<File Uid="0" Path="3DSlice146.dcm" Type="Volume" />
			<File Uid="0" Path="3DSlice147.dcm" Type="Volume" />
			<File Uid="0" Path="3DSlice148.dcm" Type="Volume" />
			<File Uid="0" Path="3DSlice149.dcm" Type="Volume" />
			<File Uid="0" Path="3DSlice15.dcm" Type="Volume" />
			<File Uid="0" Path="3DSlice150.dcm" Type="Volume" />
			<File Uid="0" Path="3DSlice151.dcm" Type="Volume" />
			<File Uid="0" Path="3DSlice152.dcm" Type="Volume" />
			<File Uid="0" Path="3DSlice153.dcm" Type="Volume" />
			<File Uid="0" Path="3DSlice154.dcm" Type="Volume" />
			<File Uid="0" Path="3DSlice155.dcm" Type="Volume" />
			<File Uid="0" Path="3DSlice156.dcm" Type="Volume" />
			<File Uid="0" Path="3DSlice157.dcm" Type="Volume" />
			<File Uid="0" Path="3DSlice158.dcm" Type="Volume" />
			<File Uid="0" Path="3DSlice159.dcm" Type="Volume" />
			<File Uid="0" Path="3DSlice16.dcm" Type="Volume" />
			<File Uid="0" Path="3DSlice160.dcm" Type="Volume" />
			<File Uid="0" Path="3DSlice161.dcm" Type="Volume" />
			<File Uid="0" Path="3DSlice162.dcm" Type="Volume" />
			<File Uid="0" Path="3DSlice163.dcm" Type="Volume" />
			<File Uid="0" Path="3DSlice164.dcm" Type="Volume" />
			<File Uid="0" Path="3DSlice165.dcm" Type="Volume" />
			<File Uid="0" Path="3DSlice166.dcm" Type="Volume" />
			<File Uid="0" Path="3DSlice167.dcm" Type="Volume" />
			<File Uid="0" Path="3DSlice168.dcm" Type="Volume" />
			<File Uid="0" Path="3DSlice169.dcm" Type="Volume" />
			<File Uid="0" Path="3DSlice17.dcm" Type="Volume" />
			<File Uid="0" Path="3DSlice170.dcm" Type="Volume" />
			<File Uid="0" Path="3DSlice171.dcm" Type="Volume" />
			<File Uid="0" Path="3DSlice172.dcm" Type="Volume" />
			<File Uid="0" Path="3DSlice173.dcm" Type="Volume" />
			<File Uid="0" Path="3DSlice174.dcm" Type="Volume" />
			<File Uid="0" Path="3DSlice175.dcm" Type="Volume" />
			<File Uid="0" Path="3DSlice176.dcm" Type="Volume" />
			<File Uid="0" Path="3DSlice177.dcm" Type="Volume" />
			<File Uid="0" Path="3DSlice178.dcm" Type="Volume" />
			<File Uid="0" Path="3DSlice179.dcm" Type="Volume" />
			<File Uid="0" Path="3DSlice18.dcm" Type="Volume" />
			<File Uid="0" Path="3DSlice180.dcm" Type="Volume" />
			<File Uid="0" Path="3DSlice181.dcm" Type="Volume" />
			<File Uid="0" Path="3DSlice182.dcm" Type="Volume" />
			<File Uid="0" Path="3DSlice183.dcm" Type="Volume" />
			<File Uid="0" Path="3DSlice184.dcm" Type="Volume" />
			<File Uid="0" Path="3DSlice185.dcm" Type="Volume" />
			<File Uid="0" Path="3DSlice186.dcm" Type="Volume" />
			<File Uid="0" Path="3DSlice187.dcm" Type="Volume" />
			<File Uid="0" Path="3DSlice188.dcm" Type="Volume" />
			<File Uid="0" Path="3DSlice189.dcm" Type="Volume" />
			<File Uid="0" Path="3DSlice19.dcm" Type="Volume" />
			<File Uid="0" Path="3DSlice190.dcm" Type="Volume" />
			<File Uid="0" Path="3DSlice191.dcm" Type="Volume" />
			<File Uid="0" Path="3DSlice192.dcm" Type="Volume" />
			<File Uid="0" Path="3DSlice193.dcm" Type="Volume" />
			<File Uid="0" Path="3DSlice194.dcm" Type="Volume" />
			<File Uid="0" Path="3DSlice195.dcm" Type="Volume" />
			<File Uid="0" Path="3DSlice196.dcm" Type="Volume" />
			<File Uid="0" Path="3DSlice197.dcm" Type="Volume" />
			<File Uid="0" Path="3DSlice198.dcm" Type="Volume" />
			<File Uid="0" Path="3DSlice199.dcm" Type="Volume" />
			<File Uid="0" Path="3DSlice2.dcm" Type="Volume" />
			<File Uid="0" Path="3DSlice20.dcm" Type="Volume" />
			<File Uid="0" Path="3DSlice200.dcm" Type="Volume" />
			<File Uid="0" Path="3DSlice201.dcm" Type="Volume" />
			<File Uid="0" Path="3DSlice202.dcm" Type="Volume" />
			<File Uid="0" Path="3DSlice203.dcm" Type="Volume" />
			<File Uid="0" Path="3DSlice204.dcm" Type="Volume" />
			<File Uid="0" Path="3DSlice205.dcm" Type="Volume" />
			<File Uid="0" Path="3DSlice206.dcm" Type="Volume" />
			<File Uid="0" Path="3DSlice207.dcm" Type="Volume" />
			<File Uid="0" Path="3DSlice208.dcm" Type="Volume" />
			<File Uid="0" Path="3DSlice209.dcm" Type="Volume" />
			<File Uid="0" Path="3DSlice21.dcm" Type="Volume" />
			<File Uid="0" Path="3DSlice210.dcm" Type="Volume" />
			<File Uid="0" Path="3DSlice211.dcm" Type="Volume" />
			<File Uid="0" Path="3DSlice212.dcm" Type="Volume" />
			<File Uid="0" Path="3DSlice213.dcm" Type="Volume" />
			<File Uid="0" Path="3DSlice214.dcm" Type="Volume" />
			<File Uid="0" Path="3DSlice215.dcm" Type="Volume" />
			<File Uid="0" Path="3DSlice216.dcm" Type="Volume" />
			<File Uid="0" Path="3DSlice217.dcm" Type="Volume" />
			<File Uid="0" Path="3DSlice218.dcm" Type="Volume" />
			<File Uid="0" Path="3DSlice219.dcm" Type="Volume" />
			<File Uid="0" Path="3DSlice22.dcm" Type="Volume" />
			<File Uid="0" Path="3DSlice220.dcm" Type="Volume" />
			<File Uid="0" Path="3DSlice221.dcm" Type="Volume" />
			<File Uid="0" Path="3DSlice222.dcm" Type="Volume" />
			<File Uid="0" Path="3DSlice223.dcm" Type="Volume" />
			<File Uid="0" Path="3DSlice224.dcm" Type="Volume" />
			<File Uid="0" Path="3DSlice225.dcm" Type="Volume" />
			<File Uid="0" Path="3DSlice226.dcm" Type="Volume" />
			<File Uid="0" Path="3DSlice227.dcm" Type="Volume" />
			<File Uid="0" Path="3DSlice228.dcm" Type="Volume" />
			<File Uid="0" Path="3DSlice229.dcm" Type="Volume" />
			<File Uid="0" Path="3DSlice23.dcm" Type="Volume" />
			<File Uid="0" Path="3DSlice230.dcm" Type="Volume" />
			<File Uid="0" Path="3DSlice231.dcm" Type="Volume" />
			<File Uid="0" Path="3DSlice232.dcm" Type="Volume" />
			<File Uid="0" Path="3DSlice233.dcm" Type="Volume" />
			<File Uid="0" Path="3DSlice234.dcm" Type="Volume" />
			<File Uid="0" Path="3DSlice235.dcm" Type="Volume" />
			<File Uid="0" Path="3DSlice236.dcm" Type="Volume" />
			<File Uid="0" Path="3DSlice237.dcm" Type="Volume" />
			<File Uid="0" Path="3DSlice238.dcm" Type="Volume" />
			<File Uid="0" Path="3DSlice239.dcm" Type="Volume" />
			<File Uid="0" Path="3DSlice24.dcm" Type="Volume" />
			<File Uid="0" Path="3DSlice240.dcm" Type="Volume" />
			<File Uid="0" Path="3DSlice241.dcm" Type="Volume" />
			<File Uid="0" Path="3DSlice242.dcm" Type="Volume" />
			<File Uid="0" Path="3DSlice243.dcm" Type="Volume" />
			<File Uid="0" Path="3DSlice244.dcm" Type="Volume" />
			<File Uid="0" Path="3DSlice245.dcm" Type="Volume" />
			<File Uid="0" Path="3DSlice246.dcm" Type="Volume" />
			<File Uid="0" Path="3DSlice247.dcm" Type="Volume" />
			<File Uid="0" Path="3DSlice248.dcm" Type="Volume" />
			<File Uid="0" Path="3DSlice249.dcm" Type="Volume" />
			<File Uid="0" Path="3DSlice25.dcm" Type="Volume" />
			<File Uid="0" Path="3DSlice250.dcm" Type="Volume" />
			<File Uid="0" Path="3DSlice251.dcm" Type="Volume" />
			<File Uid="0" Path="3DSlice252.dcm" Type="Volume" />
			<File Uid="0" Path="3DSlice253.dcm" Type="Volume" />
			<File Uid="0" Path="3DSlice254.dcm" Type="Volume" />
			<File Uid="0" Path="3DSlice255.dcm" Type="Volume" />
			<File Uid="0" Path="3DSlice256.dcm" Type="Volume" />
			<File Uid="0" Path="3DSlice257.dcm" Type="Volume" />
			<File Uid="0" Path="3DSlice258.dcm" Type="Volume" />
			<File Uid="0" Path="3DSlice259.dcm" Type="Volume" />
			<File Uid="0" Path="3DSlice26.dcm" Type="Volume" />
			<File Uid="0" Path="3DSlice260.dcm" Type="Volume" />
			<File Uid="0" Path="3DSlice261.dcm" Type="Volume" />
			<File Uid="0" Path="3DSlice262.dcm" Type="Volume" />
			<File Uid="0" Path="3DSlice263.dcm" Type="Volume" />
			<File Uid="0" Path="3DSlice264.dcm" Type="Volume" />
			<File Uid="0" Path="3DSlice265.dcm" Type="Volume" />
			<File Uid="0" Path="3DSlice266.dcm" Type="Volume" />
			<File Uid="0" Path="3DSlice267.dcm" Type="Volume" />
			<File Uid="0" Path="3DSlice268.dcm" Type="Volume" />
			<File Uid="0" Path="3DSlice269.dcm" Type="Volume" />
			<File Uid="0" Path="3DSlice27.dcm" Type="Volume" />
			<File Uid="0" Path="3DSlice270.dcm" Type="Volume" />
			<File Uid="0" Path="3DSlice271.dcm" Type="Volume" />
			<File Uid="0" Path="3DSlice272.dcm" Type="Volume" />
			<File Uid="0" Path="3DSlice273.dcm" Type="Volume" />
			<File Uid="0" Path="3DSlice274.dcm" Type="Volume" />
			<File Uid="0" Path="3DSlice275.dcm" Type="Volume" />
			<File Uid="0" Path="3DSlice276.dcm" Type="Volume" />
			<File Uid="0" Path="3DSlice277.dcm" Type="Volume" />
			<File Uid="0" Path="3DSlice278.dcm" Type="Volume" />
			<File Uid="0" Path="3DSlice279.dcm" Type="Volume" />
			<File Uid="0" Path="3DSlice28.dcm" Type="Volume" />
			<File Uid="0" Path="3DSlice280.dcm" Type="Volume" />
			<File Uid="0" Path="3DSlice281.dcm" Type="Volume" />
			<File Uid="0" Path="3DSlice282.dcm" Type="Volume" />
			<File Uid="0" Path="3DSlice283.dcm" Type="Volume" />
			<File Uid="0" Path="3DSlice284.dcm" Type="Volume" />
			<File Uid="0" Path="3DSlice285.dcm" Type="Volume" />
			<File Uid="0" Path="3DSlice286.dcm" Type="Volume" />
			<File Uid="0" Path="3DSlice287.dcm" Type="Volume" />
			<File Uid="0" Path="3DSlice288.dcm" Type="Volume" />
			<File Uid="0" Path="3DSlice289.dcm" Type="Volume" />
			<File Uid="0" Path="3DSlice29.dcm" Type="Volume" />
			<File Uid="0" Path="3DSlice290.dcm" Type="Volume" />
			<File Uid="0" Path="3DSlice291.dcm" Type="Volume" />
			<File Uid="0" Path="3DSlice292.dcm" Type="Volume" />
			<File Uid="0" Path="3DSlice293.dcm" Type="Volume" />
			<File Uid="0" Path="3DSlice294.dcm" Type="Volume" />
			<File Uid="0" Path="3DSlice295.dcm" Type="Volume" />
			<File Uid="0" Path="3DSlice296.dcm" Type="Volume" />
			<File Uid="0" Path="3DSlice297.dcm" Type="Volume" />
			<File Uid="0" Path="3DSlice298.dcm" Type="Volume" />
			<File Uid="0" Path="3DSlice299.dcm" Type="Volume" />
			<File Uid="0" Path="3DSlice3.dcm" Type="Volume" />
			<File Uid="0" Path="3DSlice30.dcm" Type="Volume" />
			<File Uid="0" Path="3DSlice300.dcm" Type="Volume" />
			<File Uid="0" Path="3DSlice301.dcm" Type="Volume" />
			<File Uid="0" Path="3DSlice302.dcm" Type="Volume" />
			<File Uid="0" Path="3DSlice303.dcm" Type="Volume" />
			<File Uid="0" Path="3DSlice304.dcm" Type="Volume" />
			<File Uid="0" Path="3DSlice305.dcm" Type="Volume" />
			<File Uid="0" Path="3DSlice306.dcm" Type="Volume" />
			<File Uid="0" Path="3DSlice307.dcm" Type="Volume" />
			<File Uid="0" Path="3DSlice308.dcm" Type="Volume" />
			<File Uid="0" Path="3DSlice309.dcm" Type="Volume" />
			<File Uid="0" Path="3DSlice31.dcm" Type="Volume" />
			<File Uid="0" Path="3DSlice310.dcm" Type="Volume" />
			<File Uid="0" Path="3DSlice311.dcm" Type="Volume" />
			<File Uid="0" Path="3DSlice312.dcm" Type="Volume" />
			<File Uid="0" Path="3DSlice313.dcm" Type="Volume" />
			<File Uid="0" Path="3DSlice314.dcm" Type="Volume" />
			<File Uid="0" Path="3DSlice315.dcm" Type="Volume" />
			<File Uid="0" Path="3DSlice316.dcm" Type="Volume" />
			<File Uid="0" Path="3DSlice317.dcm" Type="Volume" />
			<File Uid="0" Path="3DSlice318.dcm" Type="Volume" />
			<File Uid="0" Path="3DSlice319.dcm" Type="Volume" />
			<File Uid="0" Path="3DSlice32.dcm" Type="Volume" />
			<File Uid="0" Path="3DSlice320.dcm" Type="Volume" />
			<File Uid="0" Path="3DSlice321.dcm" Type="Volume" />
			<File Uid="0" Path="3DSlice322.dcm" Type="Volume" />
			<File Uid="0" Path="3DSlice323.dcm" Type="Volume" />
			<File Uid="0" Path="3DSlice324.dcm" Type="Volume" />
			<File Uid="0" Path="3DSlice325.dcm" Type="Volume" />
			<File Uid="0" Path="3DSlice326.dcm" Type="Volume" />
			<File Uid="0" Path="3DSlice327.dcm" Type="Volume" />
			<File Uid="0" Path="3DSlice328.dcm" Type="Volume" />
			<File Uid="0" Path="3DSlice329.dcm" Type="Volume" />
			<File Uid="0" Path="3DSlice33.dcm" Type="Volume" />
			<File Uid="0" Path="3DSlice330.dcm" Type="Volume" />
			<File Uid="0" Path="3DSlice331.dcm" Type="Volume" />
			<File Uid="0" Path="3DSlice332.dcm" Type="Volume" />
			<File Uid="0" Path="3DSlice333.dcm" Type="Volume" />
			<File Uid="0" Path="3DSlice334.dcm" Type="Volume" />
			<File Uid="0" Path="3DSlice335.dcm" Type="Volume" />
			<File Uid="0" Path="3DSlice336.dcm" Type="Volume" />
			<File Uid="0" Path="3DSlice337.dcm" Type="Volume" />
			<File Uid="0" Path="3DSlice338.dcm" Type="Volume" />
			<File Uid="0" Path="3DSlice339.dcm" Type="Volume" />
			<File Uid="0" Path="3DSlice34.dcm" Type="Volume" />
			<File Uid="0" Path="3DSlice340.dcm" Type="Volume" />
			<File Uid="0" Path="3DSlice341.dcm" Type="Volume" />
			<File Uid="0" Path="3DSlice342.dcm" Type="Volume" />
			<File Uid="0" Path="3DSlice343.dcm" Type="Volume" />
			<File Uid="0" Path="3DSlice344.dcm" Type="Volume" />
			<File Uid="0" Path="3DSlice345.dcm" Type="Volume" />
			<File Uid="0" Path="3DSlice346.dcm" Type="Volume" />
			<File Uid="0" Path="3DSlice35.dcm" Type="Volume" />
			<File Uid="0" Path="3DSlice36.dcm" Type="Volume" />
			<File Uid="0" Path="3DSlice37.dcm" Type="Volume" />
			<File Uid="0" Path="3DSlice38.dcm" Type="Volume" />
			<File Uid="0" Path="3DSlice39.dcm" Type="Volume" />
			<File Uid="0" Path="3DSlice4.dcm" Type="Volume" />
			<File Uid="0" Path="3DSlice40.dcm" Type="Volume" />
			<File Uid="0" Path="3DSlice41.dcm" Type="Volume" />
			<File Uid="0" Path="3DSlice42.dcm" Type="Volume" />
			<File Uid="0" Path="3DSlice43.dcm" Type="Volume" />
			<File Uid="0" Path="3DSlice44.dcm" Type="Volume" />
			<File Uid="0" Path="3DSlice45.dcm" Type="Volume" />
			<File Uid="0" Path="3DSlice46.dcm" Type="Volume" />
			<File Uid="0" Path="3DSlice47.dcm" Type="Volume" />
			<File Uid="0" Path="3DSlice48.dcm" Type="Volume" />
			<File Uid="0" Path="3DSlice49.dcm" Type="Volume" />
			<File Uid="0" Path="3DSlice5.dcm" Type="Volume" />
			<File Uid="0" Path="3DSlice50.dcm" Type="Volume" />
			<File Uid="0" Path="3DSlice51.dcm" Type="Volume" />
			<File Uid="0" Path="3DSlice52.dcm" Type="Volume" />
			<File Uid="0" Path="3DSlice53.dcm" Type="Volume" />
			<File Uid="0" Path="3DSlice54.dcm" Type="Volume" />
			<File Uid="0" Path="3DSlice55.dcm" Type="Volume" />
			<File Uid="0" Path="3DSlice56.dcm" Type="Volume" />
			<File Uid="0" Path="3DSlice57.dcm" Type="Volume" />
			<File Uid="0" Path="3DSlice58.dcm" Type="Volume" />
			<File Uid="0" Path="3DSlice59.dcm" Type="Volume" />
			<File Uid="0" Path="3DSlice6.dcm" Type="Volume" />
			<File Uid="0" Path="3DSlice60.dcm" Type="Volume" />
			<File Uid="0" Path="3DSlice61.dcm" Type="Volume" />
			<File Uid="0" Path="3DSlice62.dcm" Type="Volume" />
			<File Uid="0" Path="3DSlice63.dcm" Type="Volume" />
			<File Uid="0" Path="3DSlice64.dcm" Type="Volume" />
			<File Uid="0" Path="3DSlice65.dcm" Type="Volume" />
			<File Uid="0" Path="3DSlice66.dcm" Type="Volume" />
			<File Uid="0" Path="3DSlice67.dcm" Type="Volume" />
			<File Uid="0" Path="3DSlice68.dcm" Type="Volume" />
			<File Uid="0" Path="3DSlice69.dcm" Type="Volume" />
			<File Uid="0" Path="3DSlice7.dcm" Type="Volume" />
			<File Uid="0" Path="3DSlice70.dcm" Type="Volume" />
			<File Uid="0" Path="3DSlice71.dcm" Type="Volume" />
			<File Uid="0" Path="3DSlice72.dcm" Type="Volume" />
			<File Uid="0" Path="3DSlice73.dcm" Type="Volume" />
			<File Uid="0" Path="3DSlice74.dcm" Type="Volume" />
			<File Uid="0" Path="3DSlice75.dcm" Type="Volume" />
			<File Uid="0" Path="3DSlice76.dcm" Type="Volume" />
			<File Uid="0" Path="3DSlice77.dcm" Type="Volume" />
			<File Uid="0" Path="3DSlice78.dcm" Type="Volume" />
			<File Uid="0" Path="3DSlice79.dcm" Type="Volume" />
			<File Uid="0" Path="3DSlice8.dcm" Type="Volume" />
			<File Uid="0" Path="3DSlice80.dcm" Type="Volume" />
			<File Uid="0" Path="3DSlice81.dcm" Type="Volume" />
			<File Uid="0" Path="3DSlice82.dcm" Type="Volume" />
			<File Uid="0" Path="3DSlice83.dcm" Type="Volume" />
			<File Uid="0" Path="3DSlice84.dcm" Type="Volume" />
			<File Uid="0" Path="3DSlice85.dcm" Type="Volume" />
			<File Uid="0" Path="3DSlice86.dcm" Type="Volume" />
			<File Uid="0" Path="3DSlice87.dcm" Type="Volume" />
			<File Uid="0" Path="3DSlice88.dcm" Type="Volume" />
			<File Uid="0" Path="3DSlice89.dcm" Type="Volume" />
			<File Uid="0" Path="3DSlice9.dcm" Type="Volume" />
			<File Uid="0" Path="3DSlice90.dcm" Type="Volume" />
			<File Uid="0" Path="3DSlice91.dcm" Type="Volume" />
			<File Uid="0" Path="3DSlice92.dcm" Type="Volume" />
			<File Uid="0" Path="3DSlice93.dcm" Type="Volume" />
			<File Uid="0" Path="3DSlice94.dcm" Type="Volume" />
			<File Uid="0" Path="3DSlice95.dcm" Type="Volume" />
			<File Uid="0" Path="3DSlice96.dcm" Type="Volume" />
			<File Uid="0" Path="3DSlice97.dcm" Type="Volume" />
			<File Uid="0" Path="3DSlice98.dcm" Type="Volume" />
			<File Uid="0" Path="3DSlice99.dcm" Type="Volume" />
			<File Uid="1" Path="Analyses\1.2.250.1.90.3.3729130465.20210804152240.20568.34.xml" Type="Analysis3D" />
		</Files>
		<FilesRelations>
			<FilesRelation ParentUid="0" ChildUid="1" />
		</FilesRelations>
		<DefaultFiles>
			<DefaultFile ParentUid="0" ChildUid="1" />
		</DefaultFiles>
	</FilesManager>
</trophy>
